Workbook

Sheet Assumptions
A1: Inventory policy model: assumptions (blue cells are inputs, change them freely)
A3: Ordering cost per purchase order (GBP) | B3: 25 | C3: Assumed
A4: Annual holding cost (fraction of unit price) | B4: 0.2 | C4: Assumed
A5: Supplier lead time (weeks) | B5: 2 | C5: Assumed
A6: Service-level z value (1.645 = 95%) | B6: 1.645 | C6: Standard normal table
A7: Weeks per year | B7: 52
A8: Baseline: orders per year (monthly ordering) | B8: 12 | C8: Comparison case
A11: Demand and price inputs on the Policy sheet come from src/analysis.py (UCI Online Retail dataset, Dec 2010 to Dec 2011).

Sheet Policy
A1: Stock code | B1: Description | C1: ABC class | D1: Avg weekly demand (units) | E1: Std dev of weekly forecast error | F1: Unit price (GBP) | G1: Annual demand | H1: Holding cost per unit-year | I1: EOQ (units) | J1: Safety stock | K1: Reorder point | L1: Orders per year | M1: Annual cost at EOQ (GBP) | N1: Annual cost, monthly ordering (GBP)
A2: 22423 | B2: Regency Cakestand 3 Tier | C2: A | D2: 239.18 | E2: 133.45 | F2: 12.75 | G2: =D2*Assumptions!$B$7 -> 12437.36 | H2: =F2*Assumptions!$B$4 -> 2.55 | I2: =SQRT(2*G2*Assumptions!$B$3/H2) -> 493.83176 | J2: =Assumptions!$B$6*E2*SQRT(Assumptions!$B$5) -> 310.45559 | K2: =D2*Assumptions!$B$5+J2 -> 788.81559 | L2: =G2/I2 -> 25.18542 | M2: =G2/I2*Assumptions!$B$3+I2/2*H2 -> 1259.271 | N2: =Assumptions!$B$8*Assumptions!$B$3+(G2/Assumptions!$B$8)/2*H2 -> 1621.4695
A3: 47566 | B3: Party Bunting | C3: A | D3: 350.29 | E3: 197.18 | F3: 4.95 | G3: =D3*Assumptions!$B$7 -> 18215.08 | H3: =F3*Assumptions!$B$4 -> 0.99 | I3: =SQRT(2*G3*Assumptions!$B$3/H3) -> 959.14208 | J3: =Assumptions!$B$6*E3*SQRT(Assumptions!$B$5) -> 458.71587 | K3: =D3*Assumptions!$B$5+J3 -> 1159.2959 | L3: =G3/I3 -> 18.991013 | M3: =G3/I3*Assumptions!$B$3+I3/2*H3 -> 949.55066 | N3: =Assumptions!$B$8*Assumptions!$B$3+(G3/Assumptions!$B$8)/2*H3 -> 1051.372
A4: 85123A | B4: White Hanging Heart T-Light Holder | C4: A | D4: 615.88 | E4: 302.57 | F4: 2.95 | G4: =D4*Assumptions!$B$7 -> 32025.76 | H4: =F4*Assumptions!$B$4 -> 0.59 | I4: =SQRT(2*G4*Assumptions!$B$3/H4) -> 1647.4366 | J4: =Assumptions!$B$6*E4*SQRT(Assumptions!$B$5) -> 703.89319 | K4: =D4*Assumptions!$B$5+J4 -> 1935.6532 | L4: =G4/I4 -> 19.439752 | M4: =G4/I4*Assumptions!$B$3+I4/2*H4 -> 971.98761 | N4: =Assumptions!$B$8*Assumptions!$B$3+(G4/Assumptions!$B$8)/2*H4 -> 1087.2999
A5: 85099B | B5: Jumbo Bag Red Retrospot | C5: A | D5: 869.78 | E5: 412.66 | F5: 2.08 | G5: =D5*Assumptions!$B$7 -> 45228.56 | H5: =F5*Assumptions!$B$4 -> 0.416 | I5: =SQRT(2*G5*Assumptions!$B$3/H5) -> 2331.5499 | J5: =Assumptions!$B$6*E5*SQRT(Assumptions!$B$5) -> 960.00451 | K5: =D5*Assumptions!$B$5+J5 -> 2699.5645 | L5: =G5/I5 -> 19.398495 | M5: =G5/I5*Assumptions!$B$3+I5/2*H5 -> 969.92476 | N5: =Assumptions!$B$8*Assumptions!$B$3+(G5/Assumptions!$B$8)/2*H5 -> 1083.9617
A6: 84879 | B6: Assorted Colour Bird Ornament | C6: A | D6: 682.73 | E6: 591.36 | F6: 1.69 | G6: =D6*Assumptions!$B$7 -> 35501.96 | H6: =F6*Assumptions!$B$4 -> 0.338 | I6: =SQRT(2*G6*Assumptions!$B$3/H6) -> 2291.6739 | J6: =Assumptions!$B$6*E6*SQRT(Assumptions!$B$5) -> 1375.7289 | K6: =D6*Assumptions!$B$5+J6 -> 2741.1889 | L6: =G6/I6 -> 15.491716 | M6: =G6/I6*Assumptions!$B$3+I6/2*H6 -> 774.58578 | N6: =Assumptions!$B$8*Assumptions!$B$3+(G6/Assumptions!$B$8)/2*H6 -> 799.98594
A7: 79321 | B7: Chilli Lights | C7: A | D7: 182.88 | E7: 173.16 | F7: 5.75 | G7: =D7*Assumptions!$B$7 -> 9509.76 | H7: =F7*Assumptions!$B$4 -> 1.15 | I7: =SQRT(2*G7*Assumptions!$B$3/H7) -> 643.01464 | J7: =Assumptions!$B$6*E7*SQRT(Assumptions!$B$5) -> 402.83619 | K7: =D7*Assumptions!$B$5+J7 -> 768.59619 | L7: =G7/I7 -> 14.789337 | M7: =G7/I7*Assumptions!$B$3+I7/2*H7 -> 739.46683 | N7: =Assumptions!$B$8*Assumptions!$B$3+(G7/Assumptions!$B$8)/2*H7 -> 755.676
A8: 22197 | B8: Small Popcorn Holder | C8: A | D8: 1014.41 | E8: 778.03 | F8: 0.85 | G8: =D8*Assumptions!$B$7 -> 52749.32 | H8: =F8*Assumptions!$B$4 -> 0.17 | I8: =SQRT(2*G8*Assumptions!$B$3/H8) -> 3938.8458 | J8: =Assumptions!$B$6*E8*SQRT(Assumptions!$B$5) -> 1809.9945 | K8: =D8*Assumptions!$B$5+J8 -> 3838.8145 | L8: =G8/I8 -> 13.392076 | M8: =G8/I8*Assumptions!$B$3+I8/2*H8 -> 669.60378 | N8: =Assumptions!$B$8*Assumptions!$B$3+(G8/Assumptions!$B$8)/2*H8 -> 673.64102
A9: 21137 | B9: Black Record Cover Frame | C9: A | D9: 186.06 | E9: 218.49 | F9: 3.75 | G9: =D9*Assumptions!$B$7 -> 9675.12 | H9: =F9*Assumptions!$B$4 -> 0.75 | I9: =SQRT(2*G9*Assumptions!$B$3/H9) -> 803.1239 | J9: =Assumptions!$B$6*E9*SQRT(Assumptions!$B$5) -> 508.29105 | K9: =D9*Assumptions!$B$5+J9 -> 880.41105 | L9: =G9/I9 -> 12.046859 | M9: =G9/I9*Assumptions!$B$3+I9/2*H9 -> 602.34293 | N9: =Assumptions!$B$8*Assumptions!$B$3+(G9/Assumptions!$B$8)/2*H9 -> 602.3475
A10: 22386 | B10: Jumbo Bag Pink Polkadot | C10: A | D10: 382.35 | E10: 241.51 | F10: 2.08 | G10: =D10*Assumptions!$B$7 -> 19882.2 | H10: =F10*Assumptions!$B$4 -> 0.416 | I10: =SQRT(2*G10*Assumptions!$B$3/H10) -> 1545.8614 | J10: =Assumptions!$B$6*E10*SQRT(Assumptions!$B$5) -> 561.84435 | K10: =D10*Assumptions!$B$5+J10 -> 1326.5444 | L10: =G10/I10 -> 12.861567 | M10: =G10/I10*Assumptions!$B$3+I10/2*H10 -> 643.07835 | N10: =Assumptions!$B$8*Assumptions!$B$3+(G10/Assumptions!$B$8)/2*H10 -> 644.6248
A11: 22720 | B11: Set Of 3 Cake Tins Pantry Design | C11: A | D11: 142.98 | E11: 168.72 | F11: 4.95 | G11: =D11*Assumptions!$B$7 -> 7434.96 | H11: =F11*Assumptions!$B$4 -> 0.99 | I11: =SQRT(2*G11*Assumptions!$B$3/H11) -> 612.78302 | J11: =Assumptions!$B$6*E11*SQRT(Assumptions!$B$5) -> 392.50705 | K11: =D11*Assumptions!$B$5+J11 -> 678.46705 | L11: =G11/I11 -> 12.133104 | M11: =G11/I11*Assumptions!$B$3+I11/2*H11 -> 606.65519 | N11: =Assumptions!$B$8*Assumptions!$B$3+(G11/Assumptions!$B$8)/2*H11 -> 606.6921
A12: 22960 | B12: Jam Making Set With Jars | C12: A | D12: 161.02 | E12: 95.18 | F12: 4.25 | G12: =D12*Assumptions!$B$7 -> 8373.04 | H12: =F12*Assumptions!$B$4 -> 0.85 | I12: =SQRT(2*G12*Assumptions!$B$3/H12) -> 701.80607 | J12: =Assumptions!$B$6*E12*SQRT(Assumptions!$B$5) -> 221.42497 | K12: =D12*Assumptions!$B$5+J12 -> 543.46497 | L12: =G12/I12 -> 11.930703 | M12: =G12/I12*Assumptions!$B$3+I12/2*H12 -> 596.53516 | N12: =Assumptions!$B$8*Assumptions!$B$3+(G12/Assumptions!$B$8)/2*H12 -> 596.54517
A13: 82484 | B13: Wood Black Board Ant White Finish | C13: A | D13: 110.2 | E13: 206.92 | F13: 7.95 | G13: =D13*Assumptions!$B$7 -> 5730.4 | H13: =F13*Assumptions!$B$4 -> 1.59 | I13: =SQRT(2*G13*Assumptions!$B$3/H13) -> 424.50119 | J13: =Assumptions!$B$6*E13*SQRT(Assumptions!$B$5) -> 481.37482 | K13: =D13*Assumptions!$B$5+J13 -> 701.77482 | L13: =G13/I13 -> 13.499138 | M13: =G13/I13*Assumptions!$B$3+I13/2*H13 -> 674.95689 | N13: =Assumptions!$B$8*Assumptions!$B$3+(G13/Assumptions!$B$8)/2*H13 -> 679.639
... A77: 21485 | B77: Retrospot Heart Hot Water Bottle | C77: A | D77: 64.73 | E77: 92.42 | F77: 4.95 | G77: =D77*Assumptions!$B$7 -> 3365.96 | H77: =F77*Assumptions!$B$4 -> 0.99 | I77: =SQRT(2*G77*Assumptions!$B$3/H77) -> 412.30811 | J77: =Assumptions!$B$6*E77*SQRT(Assumptions!$B$5) -> 215.00416 | K77: =D77*Assumptions!$B$5+J77 -> 344.46416 | L77: =G77/I77 -> 8.1637006 | M77: =G77/I77*Assumptions!$B$3+I77/2*H77 -> 408.18503 | N77: =Assumptions!$B$8*Assumptions!$B$3+(G77/Assumptions!$B$8)/2*H77 -> 438.84585
B79: Total | M79: =SUM(M2:M77) -> 39727.463 | N79: =SUM(N2:N77) -> 41452.009
B80: Cost reduction vs monthly ordering | M80: =1-M79/N79 -> 0.04160344

Sheet Results
A1: ABC classification (all SKUs)
A2: Class | B2: SKUs | C2: Revenue | D2: SKU share % | E2: Revenue share %
A3: A | B3: 847 | C3: 7783842.9 | D3: 21.7 | E3: 80
A4: B | B4: 978 | C4: 1461775.6 | D4: 25.1 | E4: 15
A5: C | B5: 2070 | C5: 486868.1 | D5: 53.1 | E5: 5
A8: Forecast error on the 8-week hold-out (WAPE, lower is better)
A9: Method | B9: WAPE %
A10: Naive | B10: 59.9
A11: Moving average (4 wk) | B11: 47.8
A12: Exp. smoothing | B12: 48.5
A14: Values on this sheet are written by src/analysis.py.
